setup.py
sqlalchemy_mixins_dai/__init__.py
sqlalchemy_mixins_dai/activerecord.py
sqlalchemy_mixins_dai/eagerload.py
sqlalchemy_mixins_dai/inspection.py
sqlalchemy_mixins_dai/repr.py
sqlalchemy_mixins_dai/serialize.py
sqlalchemy_mixins_dai/session.py
sqlalchemy_mixins_dai/smartquery.py
sqlalchemy_mixins_dai/utils.py
sqlalchemy_mixins_dai.egg-info/PKG-INFO
sqlalchemy_mixins_dai.egg-info/SOURCES.txt
sqlalchemy_mixins_dai.egg-info/dependency_links.txt
sqlalchemy_mixins_dai.egg-info/not-zip-safe
sqlalchemy_mixins_dai.egg-info/requires.txt
sqlalchemy_mixins_dai.egg-info/top_level.txt